LICENSE
README.md
setup.py
dtkApi/__init__.py
dtkApi/apiRequest/Request.py
dtkApi/apiRequest/__init__.py
dtkApi/basic/ActivityLinkReq.py
dtkApi/basic/CollectionListReq.py
dtkApi/basic/CreatTaokoulingReq.py
dtkApi/basic/FirstOrderGiftMoneyReq.py
dtkApi/basic/JdGoodsLinkReq.py
dtkApi/basic/OrderDetailsReq.py
dtkApi/basic/ParseContentReq.py
dtkApi/basic/ParseTaokoulingReq.py
dtkApi/basic/PrivilegeLinkReq.py
dtkApi/basic/SuperCategoryReq.py
dtkApi/basic/TwdToTwdReq.py
dtkApi/basic/__init__.py
dtkApi/original/ActivityCatalogueReq.py
dtkApi/original/ActivityGoodsListReq.py
dtkApi/original/BrandListReq.py
dtkApi/original/CatalogueReq.py
dtkApi/original/DdqGoodsListReq.py
dtkApi/original/ExclusiveGoodsListReq.py
dtkApi/original/ExplosiveGoodsListReq.py
dtkApi/original/FriendsCircleListReq.py
dtkApi/original/GoodspriceTrendReq.py
dtkApi/original/ListSimilerGoodsByOpenReq.py
dtkApi/original/LiveMaterialGoodsListReq.py
dtkApi/original/OpGoodsListReq.py
dtkApi/original/RankingListReq.py
dtkApi/original/TbTopicListReq.py
dtkApi/original/TopicGoodsListReq.py
dtkApi/original/__init__.py
dtkApi/save/GoodsByTimeReq.py
dtkApi/save/GoodsDetailsReq.py
dtkApi/save/GoodsListReq.py
dtkApi/save/JdGoodsDetaillReq.py
dtkApi/save/NewestGoodsReq.py
dtkApi/save/StaleGoodsByTimeReq.py
dtkApi/save/__init__.py
dtkApi/search/DtkSearchGoodsReq.py
dtkApi/search/JdGoodsReq.py
dtkApi/search/ListHotWordsReq.py
dtkApi/search/PddGoodsReq.py
dtkApi/search/SuggestionReq.py
dtkApi/search/SuperGoodsReq.py
dtkApi/search/TbServiceReq.py
dtkApi/search/Top100Req.py
dtkApi/search/__init__.py
dtk_api_sdk.egg-info/PKG-INFO
dtk_api_sdk.egg-info/SOURCES.txt
dtk_api_sdk.egg-info/dependency_links.txt
dtk_api_sdk.egg-info/top_level.txt