Metadata-Version: 2.1
Name: dtk-api-sdk
Version: 1.0.3
Summary: 大淘客api
Author: zhengwj
Author-email: jun.zw@aliyun.com
License-File: LICENSE
